CHANGES.rst
MANIFEST.in
README.rst
setup.py
rattail_demo/__init__.py
rattail_demo/_version.py
rattail_demo.egg-info/PKG-INFO
rattail_demo.egg-info/SOURCES.txt
rattail_demo.egg-info/dependency_links.txt
rattail_demo.egg-info/entry_points.txt
rattail_demo.egg-info/requires.txt
rattail_demo.egg-info/top_level.txt
rattail_demo/web/__init__.py
rattail_demo/web/app.py
rattail_demo/web/templates/base.mako
rattail_demo/web/templates/home.mako
rattail_demo/web/templates/login.mako
rattail_demo/web/templates/menu.mako
rattail_demo/web/views/__init__.py
rattail_demo/web/views/auth.py
rattail_demo/web/views/common.py
rattail_demo/web/views/people.py
rattail_demo/web/views/users.py