Metadata-Version: 1.1
Name: rattail-demo
Version: 0.1.0
Summary: Rattail Software Demo
Home-page: https://rattailproject.org/
Author: Lance Edgar
Author-email: lance@edbob.org
License: UNKNOWN
Platform: UNKNOWN
Classifier: Development Status :: 3 - Alpha
Classifier: Intended Audience :: Developers
Classifier: Natural Language :: English
Classifier: Operating System :: OS Independent
Classifier: Programming Language :: Python
Classifier: Programming Language :: Python :: 2.7
Classifier: Topic :: Office/Business
Classifier: Topic :: Software Development :: Libraries :: Python Modules
